{
  "annapurna": [
    {
      "src": "/photos/annapurna/annapurna-01.jpg",
      "size": {
        "width": 2400,
        "height": 1600
      },
      "GPS": null
    },
    {
      "src": "/photos/annapurna/annapurna-02.jpg",
      "size": {
        "width": 2400,
        "height": 1600
      },
      "GPS": null
    },
    {
      "src": "/photos/annapurna/annapurna-03.jpg",
      "size": {
        "width": 2400,
        "height": 1600
      },
      "GPS": null
    },
    {
      "src": "/photos/annapurna/annapurna-04.jpg",
      "size": {
        "width": 1067,
        "height": 1600
      },
      "GPS": null
    },
    {
      "src": "/photos/annapurna/annapurna-05.jpg",
      "size": {
        "width": 1067,
        "height": 1600
      },
      "GPS": null
    },
    {
      "src": "/photos/annapurna/annapurna-06.jpg",
      "size": {
        "width": 2400,
        "height": 1600
      },
      "GPS": null
    },
    {
      "src": "/photos/annapurna/annapurna-07.jpg",
      "size": {
        "width": 2400,
        "height": 1600
      },
      "GPS": {
        "lat": 28.414108375420874,
        "lng": 84.40687173239938
      }
    },
    {
      "src": "/photos/annapurna/annapurna-08.jpg",
      "size": {
        "width": 2400,
        "height": 1600
      },
      "GPS": null
    },
    {
      "src": "/photos/annapurna/annapurna-09.jpg",
      "size": {
        "width": 1067,
        "height": 1600
      },
      "GPS": null
    },
    {
      "src": "/photos/annapurna/annapurna-10.jpg",
      "size": {
        "width": 1067,
        "height": 1600
      },
      "GPS": {
        "lat": 28.512309055291425,
        "lng": 84.36150897562582
      }
    },
    {
      "src": "/photos/annapurna/annapurna-11.jpg",
      "size": {
        "width": 2400,
        "height": 1600
      },
      "GPS": null
    },
    {
      "src": "/photos/annapurna/annapurna-12.jpg",
      "size": {
        "width": 2400,
        "height": 1600
      },
      "GPS": null
    },
    {
      "src": "/photos/annapurna/annapurna-13.jpg",
      "size": {
        "width": 2400,
        "height": 1600
      },
      "GPS": {
        "lat": 28.55081047096479,
        "lng": 84.24348785253143
      }
    },
    {
      "src": "/photos/annapurna/annapurna-14.jpg",
      "size": {
        "width": 2400,
        "height": 1600
      },
      "GPS": null
    },
    {
      "src": "/photos/annapurna/annapurna-15.jpg",
      "size": {
        "width": 1067,
        "height": 1600
      },
      "GPS": null
    },
    {
      "src": "/photos/annapurna/annapurna-16.jpg",
      "size": {
        "width": 1067,
        "height": 1600
      },
      "GPS": null
    },
    {
      "src": "/photos/annapurna/annapurna-17.jpg",
      "size": {
        "width": 2400,
        "height": 1600
      },
      "GPS": null
    },
    {
      "src": "/photos/annapurna/annapurna-18.jpg",
      "size": {
        "width": 2400,
        "height": 1600
      },
      "GPS": null
    },
    {
      "src": "/photos/annapurna/annapurna-19.jpg",
      "size": {
        "width": 2400,
        "height": 1600
      },
      "GPS": null
    },
    {
      "src": "/photos/annapurna/annapurna-20.jpg",
      "size": {
        "width": 1067,
        "height": 1600
      },
      "GPS": null
    },
    {
      "src": "/photos/annapurna/annapurna-21.jpg",
      "size": {
        "width": 1067,
        "height": 1600
      },
      "GPS": null
    },
    {
      "src": "/photos/annapurna/annapurna-22.jpg",
      "size": {
        "width": 2400,
        "height": 1600
      },
      "GPS": null
    },
    {
      "src": "/photos/annapurna/annapurna-23.jpg",
      "size": {
        "width": 1067,
        "height": 1600
      },
      "GPS": null
    },
    {
      "src": "/photos/annapurna/annapurna-24.jpg",
      "size": {
        "width": 1067,
        "height": 1600
      },
      "GPS": {
        "lat": 28.613998537365887,
        "lng": 84.14832010310455
      }
    },
    {
      "src": "/photos/annapurna/annapurna-25.jpg",
      "size": {
        "width": 2400,
        "height": 1600
      },
      "GPS": null
    },
    {
      "src": "/photos/annapurna/annapurna-26.jpg",
      "size": {
        "width": 1067,
        "height": 1600
      },
      "GPS": null
    },
    {
      "src": "/photos/annapurna/annapurna-27.jpg",
      "size": {
        "width": 1067,
        "height": 1600
      },
      "GPS": null
    },
    {
      "src": "/photos/annapurna/annapurna-28.jpg",
      "size": {
        "width": 2400,
        "height": 1600
      },
      "GPS": null
    },
    {
      "src": "/photos/annapurna/annapurna-29.jpg",
      "size": {
        "width": 2400,
        "height": 1514
      },
      "GPS": null
    },
    {
      "src": "/photos/annapurna/annapurna-30.jpg",
      "size": {
        "width": 2400,
        "height": 1600
      },
      "GPS": null
    },
    {
      "src": "/photos/annapurna/annapurna-31.jpg",
      "size": {
        "width": 2400,
        "height": 1600
      },
      "GPS": null
    },
    {
      "src": "/photos/annapurna/annapurna-32.jpg",
      "size": {
        "width": 1067,
        "height": 1600
      },
      "GPS": null
    },
    {
      "src": "/photos/annapurna/annapurna-33.jpg",
      "size": {
        "width": 1067,
        "height": 1600
      },
      "GPS": null
    },
    {
      "src": "/photos/annapurna/annapurna-34.jpg",
      "size": {
        "width": 2400,
        "height": 1600
      },
      "GPS": null
    },
    {
      "src": "/photos/annapurna/annapurna-35.jpg",
      "size": {
        "width": 2400,
        "height": 1600
      },
      "GPS": {
        "lat": 28.666876699001346,
        "lng": 84.02177067140425
      }
    },
    {
      "src": "/photos/annapurna/annapurna-36.jpg",
      "size": {
        "width": 2400,
        "height": 1600
      },
      "GPS": null
    },
    {
      "src": "/photos/annapurna/annapurna-37.jpg",
      "size": {
        "width": 2400,
        "height": 1600
      },
      "GPS": null
    },
    {
      "src": "/photos/annapurna/annapurna-38.jpg",
      "size": {
        "width": 1067,
        "height": 1600
      },
      "GPS": null
    },
    {
      "src": "/photos/annapurna/annapurna-39.jpg",
      "size": {
        "width": 1067,
        "height": 1600
      },
      "GPS": null
    },
    {
      "src": "/photos/annapurna/annapurna-40.jpg",
      "size": {
        "width": 2400,
        "height": 1600
      },
      "GPS": null
    },
    {
      "src": "/photos/annapurna/annapurna-41.jpg",
      "size": {
        "width": 2400,
        "height": 1600
      },
      "GPS": null
    },
    {
      "src": "/photos/annapurna/annapurna-42.jpg",
      "size": {
        "width": 1067,
        "height": 1600
      },
      "GPS": {
        "lat": 28.722872252520244,
        "lng": 83.97371043440297
      }
    },
    {
      "src": "/photos/annapurna/annapurna-43.jpg",
      "size": {
        "width": 1067,
        "height": 1600
      },
      "GPS": null
    },
    {
      "src": "/photos/annapurna/annapurna-44.jpg",
      "size": {
        "width": 2400,
        "height": 1600
      },
      "GPS": null
    },
    {
      "src": "/photos/annapurna/annapurna-45.jpg",
      "size": {
        "width": 1067,
        "height": 1600
      },
      "GPS": null
    },
    {
      "src": "/photos/annapurna/annapurna-46.jpg",
      "size": {
        "width": 1067,
        "height": 1600
      },
      "GPS": null
    },
    {
      "src": "/photos/annapurna/annapurna-47.jpg",
      "size": {
        "width": 2400,
        "height": 1600
      },
      "GPS": {
        "lat": 28.777207890070923,
        "lng": 83.97269375229908
      }
    },
    {
      "src": "/photos/annapurna/annapurna-48.jpg",
      "size": {
        "width": 2400,
        "height": 1600
      },
      "GPS": null
    },
    {
      "src": "/photos/annapurna/annapurna-49.jpg",
      "size": {
        "width": 2400,
        "height": 1600
      },
      "GPS": null
    },
    {
      "src": "/photos/annapurna/annapurna-50.jpg",
      "size": {
        "width": 1067,
        "height": 1600
      },
      "GPS": null
    },
    {
      "src": "/photos/annapurna/annapurna-51.jpg",
      "size": {
        "width": 1067,
        "height": 1600
      },
      "GPS": null
    },
    {
      "src": "/photos/annapurna/annapurna-52.jpg",
      "size": {
        "width": 2400,
        "height": 1600
      },
      "GPS": {
        "lat": 28.793512101910828,
        "lng": 83.93869689221086
      }
    },
    {
      "src": "/photos/annapurna/annapurna-53.jpg",
      "size": {
        "width": 2400,
        "height": 1600
      },
      "GPS": null
    },
    {
      "src": "/photos/annapurna/annapurna-54.jpg",
      "size": {
        "width": 2400,
        "height": 1600
      },
      "GPS": null
    },
    {
      "src": "/photos/annapurna/annapurna-55.jpg",
      "size": {
        "width": 1067,
        "height": 1600
      },
      "GPS": null
    },
    {
      "src": "/photos/annapurna/annapurna-56.jpg",
      "size": {
        "width": 1067,
        "height": 1600
      },
      "GPS": null
    },
    {
      "src": "/photos/annapurna/annapurna-57.jpg",
      "size": {
        "width": 2400,
        "height": 1600
      },
      "GPS": {
        "lat": 28.782227244933612,
        "lng": 83.7231679019765
      }
    }
  ],
  "bizikleta": [
    {
      "src": "/photos/bizikleta/bizikleta-01.jpg",
      "size": {
        "width": 2400,
        "height": 1600
      },
      "GPS": null
    },
    {
      "src": "/photos/bizikleta/bizikleta-02.jpg",
      "size": {
        "width": 1067,
        "height": 1600
      },
      "GPS": null
    },
    {
      "src": "/photos/bizikleta/bizikleta-03.jpg",
      "size": {
        "width": 1067,
        "height": 1600
      },
      "GPS": null
    },
    {
      "src": "/photos/bizikleta/bizikleta-04.jpg",
      "size": {
        "width": 2400,
        "height": 1600
      },
      "GPS": null
    },
    {
      "src": "/photos/bizikleta/bizikleta-05.jpg",
      "size": {
        "width": 2400,
        "height": 1600
      },
      "GPS": null
    },
    {
      "src": "/photos/bizikleta/bizikleta-06.jpg",
      "size": {
        "width": 1067,
        "height": 1600
      },
      "GPS": null
    },
    {
      "src": "/photos/bizikleta/bizikleta-07.jpg",
      "size": {
        "width": 1067,
        "height": 1600
      },
      "GPS": null
    },
    {
      "src": "/photos/bizikleta/bizikleta-08.jpg",
      "size": {
        "width": 2400,
        "height": 1600
      },
      "GPS": null
    },
    {
      "src": "/photos/bizikleta/bizikleta-09.jpg",
      "size": {
        "width": 2400,
        "height": 1600
      },
      "GPS": null
    },
    {
      "src": "/photos/bizikleta/bizikleta-10.jpg",
      "size": {
        "width": 2400,
        "height": 1600
      },
      "GPS": null
    },
    {
      "src": "/photos/bizikleta/bizikleta-11.jpg",
      "size": {
        "width": 2400,
        "height": 1600
      },
      "GPS": null
    },
    {
      "src": "/photos/bizikleta/bizikleta-12.jpg",
      "size": {
        "width": 1067,
        "height": 1600
      },
      "GPS": null
    },
    {
      "src": "/photos/bizikleta/bizikleta-13.jpg",
      "size": {
        "width": 2400,
        "height": 1600
      },
      "GPS": null
    },
    {
      "src": "/photos/bizikleta/bizikleta-14.jpg",
      "size": {
        "width": 1067,
        "height": 1600
      },
      "GPS": null
    },
    {
      "src": "/photos/bizikleta/bizikleta-15.jpg",
      "size": {
        "width": 1074,
        "height": 1600
      },
      "GPS": null
    },
    {
      "src": "/photos/bizikleta/bizikleta-16.jpg",
      "size": {
        "width": 2400,
        "height": 1600
      },
      "GPS": null
    },
    {
      "src": "/photos/bizikleta/bizikleta-17.jpg",
      "size": {
        "width": 1067,
        "height": 1600
      },
      "GPS": null
    },
    {
      "src": "/photos/bizikleta/bizikleta-18.jpg",
      "size": {
        "width": 1067,
        "height": 1600
      },
      "GPS": null
    },
    {
      "src": "/photos/bizikleta/bizikleta-19.jpg",
      "size": {
        "width": 2400,
        "height": 1600
      },
      "GPS": null
    },
    {
      "src": "/photos/bizikleta/bizikleta-20.jpg",
      "size": {
        "width": 2400,
        "height": 1600
      },
      "GPS": null
    },
    {
      "src": "/photos/bizikleta/bizikleta-21.jpg",
      "size": {
        "width": 2400,
        "height": 1600
      },
      "GPS": null
    },
    {
      "src": "/photos/bizikleta/bizikleta-22.jpg",
      "size": {
        "width": 1067,
        "height": 1600
      },
      "GPS": null
    },
    {
      "src": "/photos/bizikleta/bizikleta-23.jpg",
      "size": {
        "width": 2400,
        "height": 1600
      },
      "GPS": null
    },
    {
      "src": "/photos/bizikleta/bizikleta-24.jpg",
      "size": {
        "width": 1067,
        "height": 1600
      },
      "GPS": null
    },
    {
      "src": "/photos/bizikleta/bizikleta-25.jpg",
      "size": {
        "width": 1067,
        "height": 1600
      },
      "GPS": null
    },
    {
      "src": "/photos/bizikleta/bizikleta-26.jpg",
      "size": {
        "width": 2400,
        "height": 1600
      },
      "GPS": null
    },
    {
      "src": "/photos/bizikleta/bizikleta-27.jpg",
      "size": {
        "width": 1067,
        "height": 1600
      },
      "GPS": null
    },
    {
      "src": "/photos/bizikleta/bizikleta-28.jpg",
      "size": {
        "width": 1067,
        "height": 1600
      },
      "GPS": null
    },
    {
      "src": "/photos/bizikleta/bizikleta-29.jpg",
      "size": {
        "width": 2400,
        "height": 1600
      },
      "GPS": null
    },
    {
      "src": "/photos/bizikleta/bizikleta-30.jpg",
      "size": {
        "width": 2400,
        "height": 1600
      },
      "GPS": null
    },
    {
      "src": "/photos/bizikleta/bizikleta-31.jpg",
      "size": {
        "width": 2400,
        "height": 1600
      },
      "GPS": null
    },
    {
      "src": "/photos/bizikleta/bizikleta-32.jpg",
      "size": {
        "width": 2400,
        "height": 1600
      },
      "GPS": null
    },
    {
      "src": "/photos/bizikleta/bizikleta-33.jpg",
      "size": {
        "width": 2400,
        "height": 1600
      },
      "GPS": null
    },
    {
      "src": "/photos/bizikleta/bizikleta-34.jpg",
      "size": {
        "width": 1067,
        "height": 1600
      },
      "GPS": null
    }
  ],
  "cevennes": [
    {
      "src": "/photos/cevennes/cevennes-01.jpg",
      "size": {
        "width": 2400,
        "height": 1600
      },
      "GPS": null
    },
    {
      "src": "/photos/cevennes/cevennes-02.jpg",
      "size": {
        "width": 2400,
        "height": 1600
      },
      "GPS": null
    },
    {
      "src": "/photos/cevennes/cevennes-03.jpg",
      "size": {
        "width": 1067,
        "height": 1600
      },
      "GPS": null
    },
    {
      "src": "/photos/cevennes/cevennes-04.jpg",
      "size": {
        "width": 1067,
        "height": 1600
      },
      "GPS": null
    },
    {
      "src": "/photos/cevennes/cevennes-05.jpg",
      "size": {
        "width": 2400,
        "height": 1600
      },
      "GPS": null
    },
    {
      "src": "/photos/cevennes/cevennes-06.jpg",
      "size": {
        "width": 2400,
        "height": 1600
      },
      "GPS": null
    },
    {
      "src": "/photos/cevennes/cevennes-07.jpg",
      "size": {
        "width": 1067,
        "height": 1600
      },
      "GPS": null
    },
    {
      "src": "/photos/cevennes/cevennes-08.jpg",
      "size": {
        "width": 1067,
        "height": 1600
      },
      "GPS": null
    },
    {
      "src": "/photos/cevennes/cevennes-09.jpg",
      "size": {
        "width": 2400,
        "height": 1600
      },
      "GPS": null
    },
    {
      "src": "/photos/cevennes/cevennes-10.jpg",
      "size": {
        "width": 2400,
        "height": 1600
      },
      "GPS": null
    },
    {
      "src": "/photos/cevennes/cevennes-11.jpg",
      "size": {
        "width": 1067,
        "height": 1600
      },
      "GPS": null
    },
    {
      "src": "/photos/cevennes/cevennes-12.jpg",
      "size": {
        "width": 1067,
        "height": 1600
      },
      "GPS": null
    },
    {
      "src": "/photos/cevennes/cevennes-13.jpg",
      "size": {
        "width": 2400,
        "height": 1600
      },
      "GPS": null
    },
    {
      "src": "/photos/cevennes/cevennes-14.jpg",
      "size": {
        "width": 2400,
        "height": 1600
      },
      "GPS": null
    },
    {
      "src": "/photos/cevennes/cevennes-15.jpg",
      "size": {
        "width": 2400,
        "height": 1600
      },
      "GPS": null
    },
    {
      "src": "/photos/cevennes/cevennes-16.jpg",
      "size": {
        "width": 2400,
        "height": 1600
      },
      "GPS": null
    },
    {
      "src": "/photos/cevennes/cevennes-17.jpg",
      "size": {
        "width": 1067,
        "height": 1600
      },
      "GPS": null
    },
    {
      "src": "/photos/cevennes/cevennes-18.jpg",
      "size": {
        "width": 1067,
        "height": 1600
      },
      "GPS": null
    },
    {
      "src": "/photos/cevennes/cevennes-19.jpg",
      "size": {
        "width": 2400,
        "height": 1600
      },
      "GPS": null
    },
    {
      "src": "/photos/cevennes/cevennes-20.jpg",
      "size": {
        "width": 1067,
        "height": 1600
      },
      "GPS": null
    }
  ],
  "indonesia": [
    {
      "src": "/photos/indonesia/indonesia-01.jpg",
      "size": {
        "width": 2400,
        "height": 1600
      },
      "GPS": null
    },
    {
      "src": "/photos/indonesia/indonesia-02.jpg",
      "size": {
        "width": 2400,
        "height": 1600
      },
      "GPS": null
    },
    {
      "src": "/photos/indonesia/indonesia-03.jpg",
      "size": {
        "width": 2400,
        "height": 1600
      },
      "GPS": null
    },
    {
      "src": "/photos/indonesia/indonesia-04.jpg",
      "size": {
        "width": 2400,
        "height": 1600
      },
      "GPS": null
    },
    {
      "src": "/photos/indonesia/indonesia-05.jpg",
      "size": {
        "width": 2400,
        "height": 1600
      },
      "GPS": null
    },
    {
      "src": "/photos/indonesia/indonesia-06.jpg",
      "size": {
        "width": 2400,
        "height": 1600
      },
      "GPS": null
    },
    {
      "src": "/photos/indonesia/indonesia-07.jpg",
      "size": {
        "width": 1067,
        "height": 1600
      },
      "GPS": null
    },
    {
      "src": "/photos/indonesia/indonesia-08.jpg",
      "size": {
        "width": 1067,
        "height": 1600
      },
      "GPS": null
    },
    {
      "src": "/photos/indonesia/indonesia-09.jpg",
      "size": {
        "width": 2400,
        "height": 1600
      },
      "GPS": null
    },
    {
      "src": "/photos/indonesia/indonesia-10.jpg",
      "size": {
        "width": 2400,
        "height": 1600
      },
      "GPS": null
    },
    {
      "src": "/photos/indonesia/indonesia-11.jpg",
      "size": {
        "width": 2400,
        "height": 1600
      },
      "GPS": null
    },
    {
      "src": "/photos/indonesia/indonesia-12.jpg",
      "size": {
        "width": 1067,
        "height": 1600
      },
      "GPS": null
    },
    {
      "src": "/photos/indonesia/indonesia-13.jpg",
      "size": {
        "width": 1067,
        "height": 1600
      },
      "GPS": null
    },
    {
      "src": "/photos/indonesia/indonesia-14.jpg",
      "size": {
        "width": 2400,
        "height": 1600
      },
      "GPS": null
    },
    {
      "src": "/photos/indonesia/indonesia-15.jpg",
      "size": {
        "width": 2400,
        "height": 1600
      },
      "GPS": null
    },
    {
      "src": "/photos/indonesia/indonesia-16.jpg",
      "size": {
        "width": 1067,
        "height": 1600
      },
      "GPS": null
    },
    {
      "src": "/photos/indonesia/indonesia-17.jpg",
      "size": {
        "width": 1067,
        "height": 1600
      },
      "GPS": null
    },
    {
      "src": "/photos/indonesia/indonesia-18.jpg",
      "size": {
        "width": 2400,
        "height": 1600
      },
      "GPS": null
    },
    {
      "src": "/photos/indonesia/indonesia-19.jpg",
      "size": {
        "width": 1067,
        "height": 1600
      },
      "GPS": null
    },
    {
      "src": "/photos/indonesia/indonesia-20.jpg",
      "size": {
        "width": 1067,
        "height": 1600
      },
      "GPS": null
    },
    {
      "src": "/photos/indonesia/indonesia-21.jpg",
      "size": {
        "width": 2400,
        "height": 1600
      },
      "GPS": null
    },
    {
      "src": "/photos/indonesia/indonesia-22.jpg",
      "size": {
        "width": 1067,
        "height": 1600
      },
      "GPS": null
    },
    {
      "src": "/photos/indonesia/indonesia-23.jpg",
      "size": {
        "width": 1067,
        "height": 1600
      },
      "GPS": null
    },
    {
      "src": "/photos/indonesia/indonesia-24.jpg",
      "size": {
        "width": 2400,
        "height": 1600
      },
      "GPS": null
    },
    {
      "src": "/photos/indonesia/indonesia-25.jpg",
      "size": {
        "width": 2400,
        "height": 1600
      },
      "GPS": null
    },
    {
      "src": "/photos/indonesia/indonesia-26.jpg",
      "size": {
        "width": 1067,
        "height": 1600
      },
      "GPS": null
    },
    {
      "src": "/photos/indonesia/indonesia-27.jpg",
      "size": {
        "width": 1067,
        "height": 1600
      },
      "GPS": null
    },
    {
      "src": "/photos/indonesia/indonesia-28.jpg",
      "size": {
        "width": 2400,
        "height": 1600
      },
      "GPS": null
    },
    {
      "src": "/photos/indonesia/indonesia-29.jpg",
      "size": {
        "width": 1067,
        "height": 1600
      },
      "GPS": null
    },
    {
      "src": "/photos/indonesia/indonesia-30.jpg",
      "size": {
        "width": 1067,
        "height": 1600
      },
      "GPS": null
    },
    {
      "src": "/photos/indonesia/indonesia-31.jpg",
      "size": {
        "width": 2400,
        "height": 1600
      },
      "GPS": null
    },
    {
      "src": "/photos/indonesia/indonesia-32.jpg",
      "size": {
        "width": 1067,
        "height": 1600
      },
      "GPS": null
    },
    {
      "src": "/photos/indonesia/indonesia-33.jpg",
      "size": {
        "width": 1067,
        "height": 1600
      },
      "GPS": null
    },
    {
      "src": "/photos/indonesia/indonesia-34.jpg",
      "size": {
        "width": 2400,
        "height": 1600
      },
      "GPS": null
    },
    {
      "src": "/photos/indonesia/indonesia-35.jpg",
      "size": {
        "width": 2400,
        "height": 1600
      },
      "GPS": null
    },
    {
      "src": "/photos/indonesia/indonesia-36.jpg",
      "size": {
        "width": 2400,
        "height": 1600
      },
      "GPS": null
    },
    {
      "src": "/photos/indonesia/indonesia-37.jpg",
      "size": {
        "width": 2400,
        "height": 1600
      },
      "GPS": null
    },
    {
      "src": "/photos/indonesia/indonesia-38.jpg",
      "size": {
        "width": 1067,
        "height": 1600
      },
      "GPS": null
    },
    {
      "src": "/photos/indonesia/indonesia-39.jpg",
      "size": {
        "width": 1067,
        "height": 1600
      },
      "GPS": null
    },
    {
      "src": "/photos/indonesia/indonesia-40.jpg",
      "size": {
        "width": 2400,
        "height": 1600
      },
      "GPS": null
    },
    {
      "src": "/photos/indonesia/indonesia-41.jpg",
      "size": {
        "width": 1067,
        "height": 1600
      },
      "GPS": null
    },
    {
      "src": "/photos/indonesia/indonesia-42.jpg",
      "size": {
        "width": 1067,
        "height": 1600
      },
      "GPS": null
    },
    {
      "src": "/photos/indonesia/indonesia-43.jpg",
      "size": {
        "width": 2400,
        "height": 1600
      },
      "GPS": null
    },
    {
      "src": "/photos/indonesia/indonesia-44.jpg",
      "size": {
        "width": 1067,
        "height": 1600
      },
      "GPS": null
    },
    {
      "src": "/photos/indonesia/indonesia-45.jpg",
      "size": {
        "width": 1067,
        "height": 1600
      },
      "GPS": null
    },
    {
      "src": "/photos/indonesia/indonesia-46.jpg",
      "size": {
        "width": 1067,
        "height": 1600
      },
      "GPS": null
    },
    {
      "src": "/photos/indonesia/indonesia-47.jpg",
      "size": {
        "width": 2400,
        "height": 1600
      },
      "GPS": null
    },
    {
      "src": "/photos/indonesia/indonesia-48.jpg",
      "size": {
        "width": 1067,
        "height": 1600
      },
      "GPS": null
    },
    {
      "src": "/photos/indonesia/indonesia-49.jpg",
      "size": {
        "width": 1067,
        "height": 1600
      },
      "GPS": null
    },
    {
      "src": "/photos/indonesia/indonesia-50.jpg",
      "size": {
        "width": 2400,
        "height": 1600
      },
      "GPS": null
    },
    {
      "src": "/photos/indonesia/indonesia-51.jpg",
      "size": {
        "width": 1067,
        "height": 1600
      },
      "GPS": null
    },
    {
      "src": "/photos/indonesia/indonesia-52.jpg",
      "size": {
        "width": 1067,
        "height": 1600
      },
      "GPS": null
    },
    {
      "src": "/photos/indonesia/indonesia-53.jpg",
      "size": {
        "width": 2400,
        "height": 1600
      },
      "GPS": null
    },
    {
      "src": "/photos/indonesia/indonesia-54.jpg",
      "size": {
        "width": 1067,
        "height": 1600
      },
      "GPS": null
    },
    {
      "src": "/photos/indonesia/indonesia-55.jpg",
      "size": {
        "width": 1067,
        "height": 1600
      },
      "GPS": null
    },
    {
      "src": "/photos/indonesia/indonesia-56.jpg",
      "size": {
        "width": 1067,
        "height": 1600
      },
      "GPS": null
    },
    {
      "src": "/photos/indonesia/indonesia-57.jpg",
      "size": {
        "width": 1067,
        "height": 1600
      },
      "GPS": null
    },
    {
      "src": "/photos/indonesia/indonesia-58.jpg",
      "size": {
        "width": 2400,
        "height": 1600
      },
      "GPS": null
    },
    {
      "src": "/photos/indonesia/indonesia-59.jpg",
      "size": {
        "width": 1067,
        "height": 1600
      },
      "GPS": null
    },
    {
      "src": "/photos/indonesia/indonesia-60.jpg",
      "size": {
        "width": 1067,
        "height": 1600
      },
      "GPS": null
    },
    {
      "src": "/photos/indonesia/indonesia-61.jpg",
      "size": {
        "width": 2400,
        "height": 1600
      },
      "GPS": null
    },
    {
      "src": "/photos/indonesia/indonesia-62.jpg",
      "size": {
        "width": 1067,
        "height": 1600
      },
      "GPS": null
    },
    {
      "src": "/photos/indonesia/indonesia-63.jpg",
      "size": {
        "width": 1067,
        "height": 1600
      },
      "GPS": null
    },
    {
      "src": "/photos/indonesia/indonesia-64.jpg",
      "size": {
        "width": 2400,
        "height": 1600
      },
      "GPS": null
    },
    {
      "src": "/photos/indonesia/indonesia-65.jpg",
      "size": {
        "width": 1067,
        "height": 1600
      },
      "GPS": null
    },
    {
      "src": "/photos/indonesia/indonesia-66.jpg",
      "size": {
        "width": 1067,
        "height": 1600
      },
      "GPS": null
    },
    {
      "src": "/photos/indonesia/indonesia-67.jpg",
      "size": {
        "width": 2400,
        "height": 1600
      },
      "GPS": null
    },
    {
      "src": "/photos/indonesia/indonesia-68.jpg",
      "size": {
        "width": 1067,
        "height": 1600
      },
      "GPS": null
    },
    {
      "src": "/photos/indonesia/indonesia-69.jpg",
      "size": {
        "width": 1067,
        "height": 1600
      },
      "GPS": null
    },
    {
      "src": "/photos/indonesia/indonesia-70.jpg",
      "size": {
        "width": 2400,
        "height": 1600
      },
      "GPS": null
    },
    {
      "src": "/photos/indonesia/indonesia-71.jpg",
      "size": {
        "width": 1067,
        "height": 1600
      },
      "GPS": null
    },
    {
      "src": "/photos/indonesia/indonesia-72.jpg",
      "size": {
        "width": 1067,
        "height": 1600
      },
      "GPS": null
    },
    {
      "src": "/photos/indonesia/indonesia-73.jpg",
      "size": {
        "width": 2400,
        "height": 1600
      },
      "GPS": null
    },
    {
      "src": "/photos/indonesia/indonesia-74.jpg",
      "size": {
        "width": 1067,
        "height": 1600
      },
      "GPS": null
    },
    {
      "src": "/photos/indonesia/indonesia-75.jpg",
      "size": {
        "width": 2400,
        "height": 1600
      },
      "GPS": null
    },
    {
      "src": "/photos/indonesia/indonesia-76.jpg",
      "size": {
        "width": 1067,
        "height": 1600
      },
      "GPS": null
    },
    {
      "src": "/photos/indonesia/indonesia-77.jpg",
      "size": {
        "width": 1067,
        "height": 1600
      },
      "GPS": null
    }
  ],
  "istanbul": [
    {
      "src": "/photos/istanbul/istanbul-01.jpg",
      "size": {
        "width": 2400,
        "height": 1600
      },
      "GPS": null
    },
    {
      "src": "/photos/istanbul/istanbul-02.jpg",
      "size": {
        "width": 2400,
        "height": 1600
      },
      "GPS": null
    },
    {
      "src": "/photos/istanbul/istanbul-03.jpg",
      "size": {
        "width": 2400,
        "height": 1600
      },
      "GPS": null
    },
    {
      "src": "/photos/istanbul/istanbul-04.jpg",
      "size": {
        "width": 1067,
        "height": 1600
      },
      "GPS": null
    },
    {
      "src": "/photos/istanbul/istanbul-05.jpg",
      "size": {
        "width": 1067,
        "height": 1600
      },
      "GPS": null
    },
    {
      "src": "/photos/istanbul/istanbul-06.jpg",
      "size": {
        "width": 2400,
        "height": 1600
      },
      "GPS": null
    },
    {
      "src": "/photos/istanbul/istanbul-07.jpg",
      "size": {
        "width": 2400,
        "height": 1600
      },
      "GPS": null
    },
    {
      "src": "/photos/istanbul/istanbul-08.jpg",
      "size": {
        "width": 2400,
        "height": 1600
      },
      "GPS": null
    },
    {
      "src": "/photos/istanbul/istanbul-09.jpg",
      "size": {
        "width": 2400,
        "height": 1600
      },
      "GPS": null
    },
    {
      "src": "/photos/istanbul/istanbul-10.jpg",
      "size": {
        "width": 2400,
        "height": 1600
      },
      "GPS": null
    },
    {
      "src": "/photos/istanbul/istanbul-11.jpg",
      "size": {
        "width": 2400,
        "height": 1600
      },
      "GPS": null
    },
    {
      "src": "/photos/istanbul/istanbul-12.jpg",
      "size": {
        "width": 2400,
        "height": 1600
      },
      "GPS": null
    },
    {
      "src": "/photos/istanbul/istanbul-13.jpg",
      "size": {
        "width": 1067,
        "height": 1600
      },
      "GPS": null
    },
    {
      "src": "/photos/istanbul/istanbul-14.jpg",
      "size": {
        "width": 1067,
        "height": 1600
      },
      "GPS": null
    },
    {
      "src": "/photos/istanbul/istanbul-15.jpg",
      "size": {
        "width": 2400,
        "height": 1600
      },
      "GPS": null
    },
    {
      "src": "/photos/istanbul/istanbul-16.jpg",
      "size": {
        "width": 2400,
        "height": 1600
      },
      "GPS": null
    },
    {
      "src": "/photos/istanbul/istanbul-17.jpg",
      "size": {
        "width": 2400,
        "height": 1600
      },
      "GPS": null
    },
    {
      "src": "/photos/istanbul/istanbul-18.jpg",
      "size": {
        "width": 2400,
        "height": 1600
      },
      "GPS": null
    },
    {
      "src": "/photos/istanbul/istanbul-19.jpg",
      "size": {
        "width": 2400,
        "height": 1600
      },
      "GPS": null
    },
    {
      "src": "/photos/istanbul/istanbul-20.jpg",
      "size": {
        "width": 2400,
        "height": 1600
      },
      "GPS": null
    },
    {
      "src": "/photos/istanbul/istanbul-21.jpg",
      "size": {
        "width": 2400,
        "height": 1600
      },
      "GPS": null
    },
    {
      "src": "/photos/istanbul/istanbul-22.jpg",
      "size": {
        "width": 2400,
        "height": 1600
      },
      "GPS": null
    },
    {
      "src": "/photos/istanbul/istanbul-23.jpg",
      "size": {
        "width": 1067,
        "height": 1600
      },
      "GPS": null
    },
    {
      "src": "/photos/istanbul/istanbul-24.jpg",
      "size": {
        "width": 1067,
        "height": 1600
      },
      "GPS": null
    },
    {
      "src": "/photos/istanbul/istanbul-25.jpg",
      "size": {
        "width": 2400,
        "height": 1600
      },
      "GPS": null
    },
    {
      "src": "/photos/istanbul/istanbul-26.jpg",
      "size": {
        "width": 2400,
        "height": 1600
      },
      "GPS": null
    },
    {
      "src": "/photos/istanbul/istanbul-27.jpg",
      "size": {
        "width": 1067,
        "height": 1600
      },
      "GPS": null
    },
    {
      "src": "/photos/istanbul/istanbul-28.jpg",
      "size": {
        "width": 1067,
        "height": 1600
      },
      "GPS": null
    },
    {
      "src": "/photos/istanbul/istanbul-29.jpg",
      "size": {
        "width": 2400,
        "height": 1600
      },
      "GPS": null
    },
    {
      "src": "/photos/istanbul/istanbul-30.jpg",
      "size": {
        "width": 2400,
        "height": 1600
      },
      "GPS": null
    }
  ],
  "japan": [
    {
      "src": "/photos/japan/japon-001.jpg",
      "size": {
        "width": 1067,
        "height": 1600
      },
      "GPS": null
    },
    {
      "src": "/photos/japan/japon-002.jpg",
      "size": {
        "width": 1067,
        "height": 1600
      },
      "GPS": null
    },
    {
      "src": "/photos/japan/japon-003.jpg",
      "size": {
        "width": 2400,
        "height": 1600
      },
      "GPS": null
    },
    {
      "src": "/photos/japan/japon-004.jpg",
      "size": {
        "width": 1067,
        "height": 1600
      },
      "GPS": null
    },
    {
      "src": "/photos/japan/japon-005.jpg",
      "size": {
        "width": 1067,
        "height": 1600
      },
      "GPS": null
    },
    {
      "src": "/photos/japan/japon-006.jpg",
      "size": {
        "width": 2400,
        "height": 1600
      },
      "GPS": null
    },
    {
      "src": "/photos/japan/japon-007.jpg",
      "size": {
        "width": 1067,
        "height": 1600
      },
      "GPS": null
    },
    {
      "src": "/photos/japan/japon-008.jpg",
      "size": {
        "width": 1067,
        "height": 1600
      },
      "GPS": null
    },
    {
      "src": "/photos/japan/japon-009.jpg",
      "size": {
        "width": 2400,
        "height": 1600
      },
      "GPS": null
    },
    {
      "src": "/photos/japan/japon-010.jpg",
      "size": {
        "width": 2400,
        "height": 1600
      },
      "GPS": null
    },
    {
      "src": "/photos/japan/japon-011.jpg",
      "size": {
        "width": 1067,
        "height": 1600
      },
      "GPS": {
        "lat": 26.213058302430984,
        "lng": 127.6914229763004
      }
    },
    {
      "src": "/photos/japan/japon-012.jpg",
      "size": {
        "width": 1067,
        "height": 1600
      },
      "GPS": null
    },
    {
      "src": "/photos/japan/japon-013.jpg",
      "size": {
        "width": 2400,
        "height": 1600
      },
      "GPS": null
    },
    {
      "src": "/photos/japan/japon-014.jpg",
      "size": {
        "width": 1067,
        "height": 1600
      },
      "GPS": null
    },
    {
      "src": "/photos/japan/japon-015.jpg",
      "size": {
        "width": 1067,
        "height": 1600
      },
      "GPS": null
    },
    {
      "src": "/photos/japan/japon-016.jpg",
      "size": {
        "width": 2400,
        "height": 1600
      },
      "GPS": null
    },
    {
      "src": "/photos/japan/japon-017.jpg",
      "size": {
        "width": 1067,
        "height": 1600
      },
      "GPS": null
    },
    {
      "src": "/photos/japan/japon-018.jpg",
      "size": {
        "width": 1067,
        "height": 1600
      },
      "GPS": null
    },
    {
      "src": "/photos/japan/japon-019.jpg",
      "size": {
        "width": 2400,
        "height": 1600
      },
      "GPS": null
    },
    {
      "src": "/photos/japan/japon-020.jpg",
      "size": {
        "width": 1067,
        "height": 1600
      },
      "GPS": null
    },
    {
      "src": "/photos/japan/japon-021.jpg",
      "size": {
        "width": 1067,
        "height": 1600
      },
      "GPS": null
    },
    {
      "src": "/photos/japan/japon-022.jpg",
      "size": {
        "width": 2400,
        "height": 1600
      },
      "GPS": null
    },
    {
      "src": "/photos/japan/japon-023.jpg",
      "size": {
        "width": 1067,
        "height": 1600
      },
      "GPS": null
    },
    {
      "src": "/photos/japan/japon-024.jpg",
      "size": {
        "width": 1067,
        "height": 1600
      },
      "GPS": null
    },
    {
      "src": "/photos/japan/japon-025.jpg",
      "size": {
        "width": 2400,
        "height": 1600
      },
      "GPS": null
    },
    {
      "src": "/photos/japan/japon-026.jpg",
      "size": {
        "width": 1067,
        "height": 1600
      },
      "GPS": null
    },
    {
      "src": "/photos/japan/japon-027.jpg",
      "size": {
        "width": 1067,
        "height": 1600
      },
      "GPS": null
    },
    {
      "src": "/photos/japan/japon-028.jpg",
      "size": {
        "width": 2400,
        "height": 1600
      },
      "GPS": null
    },
    {
      "src": "/photos/japan/japon-029.jpg",
      "size": {
        "width": 1067,
        "height": 1600
      },
      "GPS": {
        "lat": 24.453064984236423,
        "lng": 124.14440009386367
      }
    },
    {
      "src": "/photos/japan/japon-030.jpg",
      "size": {
        "width": 1067,
        "height": 1600
      },
      "GPS": null
    },
    {
      "src": "/photos/japan/japon-031.jpg",
      "size": {
        "width": 2400,
        "height": 1600
      },
      "GPS": null
    },
    {
      "src": "/photos/japan/japon-032.jpg",
      "size": {
        "width": 1067,
        "height": 1600
      },
      "GPS": null
    },
    {
      "src": "/photos/japan/japon-033.jpg",
      "size": {
        "width": 1067,
        "height": 1600
      },
      "GPS": null
    },
    {
      "src": "/photos/japan/japon-034.jpg",
      "size": {
        "width": 2400,
        "height": 1600
      },
      "GPS": {
        "lat": 24.325626378960376,
        "lng": 124.08793913875908
      }
    },
    {
      "src": "/photos/japan/japon-035.jpg",
      "size": {
        "width": 1067,
        "height": 1600
      },
      "GPS": null
    },
    {
      "src": "/photos/japan/japon-036.jpg",
      "size": {
        "width": 1067,
        "height": 1600
      },
      "GPS": null
    },
    {
      "src": "/photos/japan/japon-037.jpg",
      "size": {
        "width": 2400,
        "height": 1600
      },
      "GPS": null
    },
    {
      "src": "/photos/japan/japon-038.jpg",
      "size": {
        "width": 1067,
        "height": 1600
      },
      "GPS": null
    },
    {
      "src": "/photos/japan/japon-039.jpg",
      "size": {
        "width": 1067,
        "height": 1600
      },
      "GPS": null
    },
    {
      "src": "/photos/japan/japon-040.jpg",
      "size": {
        "width": 2400,
        "height": 1600
      },
      "GPS": null
    },
    {
      "src": "/photos/japan/japon-041.jpg",
      "size": {
        "width": 1067,
        "height": 1600
      },
      "GPS": {
        "lat": 24.338961828454625,
        "lng": 123.82143392908412
      }
    },
    {
      "src": "/photos/japan/japon-042.jpg",
      "size": {
        "width": 1067,
        "height": 1600
      },
      "GPS": null
    },
    {
      "src": "/photos/japan/japon-043.jpg",
      "size": {
        "width": 2400,
        "height": 1600
      },
      "GPS": null
    },
    {
      "src": "/photos/japan/japon-044.jpg",
      "size": {
        "width": 1067,
        "height": 1600
      },
      "GPS": null
    },
    {
      "src": "/photos/japan/japon-045.jpg",
      "size": {
        "width": 1067,
        "height": 1600
      },
      "GPS": null
    },
    {
      "src": "/photos/japan/japon-046.jpg",
      "size": {
        "width": 2400,
        "height": 1600
      },
      "GPS": null
    },
    {
      "src": "/photos/japan/japon-047.jpg",
      "size": {
        "width": 1067,
        "height": 1600
      },
      "GPS": null
    },
    {
      "src": "/photos/japan/japon-048.jpg",
      "size": {
        "width": 1067,
        "height": 1600
      },
      "GPS": null
    },
    {
      "src": "/photos/japan/japon-049.jpg",
      "size": {
        "width": 2400,
        "height": 1600
      },
      "GPS": null
    },
    {
      "src": "/photos/japan/japon-050.jpg",
      "size": {
        "width": 1067,
        "height": 1600
      },
      "GPS": null
    },
    {
      "src": "/photos/japan/japon-051.jpg",
      "size": {
        "width": 1067,
        "height": 1600
      },
      "GPS": null
    },
    {
      "src": "/photos/japan/japon-052.jpg",
      "size": {
        "width": 2400,
        "height": 1600
      },
      "GPS": null
    },
    {
      "src": "/photos/japan/japon-053.jpg",
      "size": {
        "width": 1067,
        "height": 1600
      },
      "GPS": null
    },
    {
      "src": "/photos/japan/japon-054.jpg",
      "size": {
        "width": 1067,
        "height": 1600
      },
      "GPS": null
    },
    {
      "src": "/photos/japan/japon-055.jpg",
      "size": {
        "width": 2400,
        "height": 1600
      },
      "GPS": null
    },
    {
      "src": "/photos/japan/japon-056.jpg",
      "size": {
        "width": 2400,
        "height": 1600
      },
      "GPS": null
    },
    {
      "src": "/photos/japan/japon-057.jpg",
      "size": {
        "width": 1067,
        "height": 1600
      },
      "GPS": null
    },
    {
      "src": "/photos/japan/japon-058.jpg",
      "size": {
        "width": 1067,
        "height": 1600
      },
      "GPS": null
    },
    {
      "src": "/photos/japan/japon-059.jpg",
      "size": {
        "width": 2400,
        "height": 1600
      },
      "GPS": null
    },
    {
      "src": "/photos/japan/japon-060.jpg",
      "size": {
        "width": 2400,
        "height": 1600
      },
      "GPS": {
        "lat": 26.232553449372116,
        "lng": 127.30723757309941
      }
    },
    {
      "src": "/photos/japan/japon-061.jpg",
      "size": {
        "width": 1067,
        "height": 1600
      },
      "GPS": null
    },
    {
      "src": "/photos/japan/japon-062.jpg",
      "size": {
        "width": 1067,
        "height": 1600
      },
      "GPS": null
    },
    {
      "src": "/photos/japan/japon-063.jpg",
      "size": {
        "width": 2400,
        "height": 1600
      },
      "GPS": null
    },
    {
      "src": "/photos/japan/japon-064.jpg",
      "size": {
        "width": 1067,
        "height": 1600
      },
      "GPS": null
    },
    {
      "src": "/photos/japan/japon-065.jpg",
      "size": {
        "width": 1067,
        "height": 1600
      },
      "GPS": null
    },
    {
      "src": "/photos/japan/japon-066.jpg",
      "size": {
        "width": 2400,
        "height": 1600
      },
      "GPS": null
    },
    {
      "src": "/photos/japan/japon-067.jpg",
      "size": {
        "width": 1067,
        "height": 1600
      },
      "GPS": null
    },
    {
      "src": "/photos/japan/japon-068.jpg",
      "size": {
        "width": 1067,
        "height": 1600
      },
      "GPS": null
    },
    {
      "src": "/photos/japan/japon-069.jpg",
      "size": {
        "width": 2400,
        "height": 1600
      },
      "GPS": null
    },
    {
      "src": "/photos/japan/japon-070.jpg",
      "size": {
        "width": 2400,
        "height": 1600
      },
      "GPS": null
    },
    {
      "src": "/photos/japan/japon-071.jpg",
      "size": {
        "width": 1067,
        "height": 1600
      },
      "GPS": null
    },
    {
      "src": "/photos/japan/japon-072.jpg",
      "size": {
        "width": 1067,
        "height": 1600
      },
      "GPS": null
    },
    {
      "src": "/photos/japan/japon-073.jpg",
      "size": {
        "width": 2400,
        "height": 1600
      },
      "GPS": null
    },
    {
      "src": "/photos/japan/japon-074.jpg",
      "size": {
        "width": 1067,
        "height": 1600
      },
      "GPS": null
    },
    {
      "src": "/photos/japan/japon-075.jpg",
      "size": {
        "width": 1067,
        "height": 1600
      },
      "GPS": null
    },
    {
      "src": "/photos/japan/japon-076.jpg",
      "size": {
        "width": 2400,
        "height": 1600
      },
      "GPS": null
    },
    {
      "src": "/photos/japan/japon-077.jpg",
      "size": {
        "width": 2399,
        "height": 1600
      },
      "GPS": null
    },
    {
      "src": "/photos/japan/japon-078.jpg",
      "size": {
        "width": 2400,
        "height": 1600
      },
      "GPS": {
        "lat": 30.347614733934222,
        "lng": 130.52601043182923
      }
    },
    {
      "src": "/photos/japan/japon-079.jpg",
      "size": {
        "width": 2400,
        "height": 1600
      },
      "GPS": null
    },
    {
      "src": "/photos/japan/japon-080.jpg",
      "size": {
        "width": 1067,
        "height": 1600
      },
      "GPS": null
    },
    {
      "src": "/photos/japan/japon-081.jpg",
      "size": {
        "width": 1067,
        "height": 1600
      },
      "GPS": null
    },
    {
      "src": "/photos/japan/japon-082.jpg",
      "size": {
        "width": 2400,
        "height": 1600
      },
      "GPS": null
    },
    {
      "src": "/photos/japan/japon-083.jpg",
      "size": {
        "width": 1067,
        "height": 1600
      },
      "GPS": null
    },
    {
      "src": "/photos/japan/japon-084.jpg",
      "size": {
        "width": 1067,
        "height": 1600
      },
      "GPS": null
    },
    {
      "src": "/photos/japan/japon-085.jpg",
      "size": {
        "width": 2400,
        "height": 1600
      },
      "GPS": null
    },
    {
      "src": "/photos/japan/japon-086.jpg",
      "size": {
        "width": 2400,
        "height": 1600
      },
      "GPS": null
    },
    {
      "src": "/photos/japan/japon-087.jpg",
      "size": {
        "width": 1067,
        "height": 1600
      },
      "GPS": null
    },
    {
      "src": "/photos/japan/japon-088.jpg",
      "size": {
        "width": 1067,
        "height": 1600
      },
      "GPS": null
    },
    {
      "src": "/photos/japan/japon-089.jpg",
      "size": {
        "width": 2400,
        "height": 1600
      },
      "GPS": null
    },
    {
      "src": "/photos/japan/japon-090.jpg",
      "size": {
        "width": 1067,
        "height": 1600
      },
      "GPS": null
    },
    {
      "src": "/photos/japan/japon-091.jpg",
      "size": {
        "width": 1067,
        "height": 1600
      },
      "GPS": null
    },
    {
      "src": "/photos/japan/japon-092.jpg",
      "size": {
        "width": 2400,
        "height": 1600
      },
      "GPS": null
    },
    {
      "src": "/photos/japan/japon-093.jpg",
      "size": {
        "width": 1067,
        "height": 1600
      },
      "GPS": null
    },
    {
      "src": "/photos/japan/japon-094.jpg",
      "size": {
        "width": 1067,
        "height": 1600
      },
      "GPS": null
    },
    {
      "src": "/photos/japan/japon-095.jpg",
      "size": {
        "width": 2400,
        "height": 1600
      },
      "GPS": null
    },
    {
      "src": "/photos/japan/japon-096.jpg",
      "size": {
        "width": 2400,
        "height": 1600
      },
      "GPS": null
    },
    {
      "src": "/photos/japan/japon-097.jpg",
      "size": {
        "width": 1067,
        "height": 1600
      },
      "GPS": null
    },
    {
      "src": "/photos/japan/japon-098.jpg",
      "size": {
        "width": 1067,
        "height": 1600
      },
      "GPS": null
    },
    {
      "src": "/photos/japan/japon-099.jpg",
      "size": {
        "width": 2400,
        "height": 1600
      },
      "GPS": null
    },
    {
      "src": "/photos/japan/japon-100.jpg",
      "size": {
        "width": 1067,
        "height": 1600
      },
      "GPS": null
    },
    {
      "src": "/photos/japan/japon-101.jpg",
      "size": {
        "width": 1067,
        "height": 1600
      },
      "GPS": null
    }
  ],
  "kilimanjaro": [
    {
      "src": "/photos/kilimanjaro/kilimanjaro-01.jpg",
      "size": {
        "width": 1067,
        "height": 1600
      },
      "GPS": null
    },
    {
      "src": "/photos/kilimanjaro/kilimanjaro-02.jpg",
      "size": {
        "width": 2400,
        "height": 1600
      },
      "GPS": null
    },
    {
      "src": "/photos/kilimanjaro/kilimanjaro-03.jpg",
      "size": {
        "width": 2400,
        "height": 1600
      },
      "GPS": null
    },
    {
      "src": "/photos/kilimanjaro/kilimanjaro-04.jpg",
      "size": {
        "width": 2400,
        "height": 1600
      },
      "GPS": null
    },
    {
      "src": "/photos/kilimanjaro/kilimanjaro-05.jpg",
      "size": {
        "width": 2400,
        "height": 1600
      },
      "GPS": null
    },
    {
      "src": "/photos/kilimanjaro/kilimanjaro-06.jpg",
      "size": {
        "width": 2400,
        "height": 1600
      },
      "GPS": null
    },
    {
      "src": "/photos/kilimanjaro/kilimanjaro-07.jpg",
      "size": {
        "width": 2400,
        "height": 1600
      },
      "GPS": null
    },
    {
      "src": "/photos/kilimanjaro/kilimanjaro-08.jpg",
      "size": {
        "width": 2400,
        "height": 1600
      },
      "GPS": null
    },
    {
      "src": "/photos/kilimanjaro/kilimanjaro-09.jpg",
      "size": {
        "width": 2400,
        "height": 1600
      },
      "GPS": null
    },
    {
      "src": "/photos/kilimanjaro/kilimanjaro-10.jpg",
      "size": {
        "width": 2400,
        "height": 1600
      },
      "GPS": null
    },
    {
      "src": "/photos/kilimanjaro/kilimanjaro-11.jpg",
      "size": {
        "width": 2400,
        "height": 1600
      },
      "GPS": null
    },
    {
      "src": "/photos/kilimanjaro/kilimanjaro-12.jpg",
      "size": {
        "width": 2400,
        "height": 1600
      },
      "GPS": null
    },
    {
      "src": "/photos/kilimanjaro/kilimanjaro-13.jpg",
      "size": {
        "width": 2400,
        "height": 1600
      },
      "GPS": null
    },
    {
      "src": "/photos/kilimanjaro/kilimanjaro-14.jpg",
      "size": {
        "width": 2400,
        "height": 1600
      },
      "GPS": null
    },
    {
      "src": "/photos/kilimanjaro/kilimanjaro-15.jpg",
      "size": {
        "width": 2400,
        "height": 1600
      },
      "GPS": null
    },
    {
      "src": "/photos/kilimanjaro/kilimanjaro-16.jpg",
      "size": {
        "width": 2400,
        "height": 1600
      },
      "GPS": null
    },
    {
      "src": "/photos/kilimanjaro/kilimanjaro-17.jpg",
      "size": {
        "width": 1067,
        "height": 1600
      },
      "GPS": null
    },
    {
      "src": "/photos/kilimanjaro/kilimanjaro-18.jpg",
      "size": {
        "width": 2400,
        "height": 1600
      },
      "GPS": null
    },
    {
      "src": "/photos/kilimanjaro/kilimanjaro-19.jpg",
      "size": {
        "width": 2400,
        "height": 1600
      },
      "GPS": null
    },
    {
      "src": "/photos/kilimanjaro/kilimanjaro-20.jpg",
      "size": {
        "width": 2400,
        "height": 1600
      },
      "GPS": null
    },
    {
      "src": "/photos/kilimanjaro/kilimanjaro-21.jpg",
      "size": {
        "width": 2400,
        "height": 1600
      },
      "GPS": null
    },
    {
      "src": "/photos/kilimanjaro/kilimanjaro-22.jpg",
      "size": {
        "width": 2400,
        "height": 1600
      },
      "GPS": null
    },
    {
      "src": "/photos/kilimanjaro/kilimanjaro-23.jpg",
      "size": {
        "width": 2400,
        "height": 1600
      },
      "GPS": null
    },
    {
      "src": "/photos/kilimanjaro/kilimanjaro-24.jpg",
      "size": {
        "width": 2400,
        "height": 1600
      },
      "GPS": null
    },
    {
      "src": "/photos/kilimanjaro/kilimanjaro-25.jpg",
      "size": {
        "width": 2400,
        "height": 1600
      },
      "GPS": null
    },
    {
      "src": "/photos/kilimanjaro/kilimanjaro-26.jpg",
      "size": {
        "width": 2400,
        "height": 1600
      },
      "GPS": null
    },
    {
      "src": "/photos/kilimanjaro/kilimanjaro-27.jpg",
      "size": {
        "width": 2400,
        "height": 1600
      },
      "GPS": null
    },
    {
      "src": "/photos/kilimanjaro/kilimanjaro-28.jpg",
      "size": {
        "width": 2400,
        "height": 1600
      },
      "GPS": null
    },
    {
      "src": "/photos/kilimanjaro/kilimanjaro-29.jpg",
      "size": {
        "width": 2396,
        "height": 1600
      },
      "GPS": null
    },
    {
      "src": "/photos/kilimanjaro/kilimanjaro-30.jpg",
      "size": {
        "width": 2400,
        "height": 1600
      },
      "GPS": null
    },
    {
      "src": "/photos/kilimanjaro/kilimanjaro-31.jpg",
      "size": {
        "width": 1067,
        "height": 1600
      },
      "GPS": null
    },
    {
      "src": "/photos/kilimanjaro/kilimanjaro-32.jpg",
      "size": {
        "width": 2400,
        "height": 1600
      },
      "GPS": null
    },
    {
      "src": "/photos/kilimanjaro/kilimanjaro-33.jpg",
      "size": {
        "width": 2400,
        "height": 1600
      },
      "GPS": null
    },
    {
      "src": "/photos/kilimanjaro/kilimanjaro-34.jpg",
      "size": {
        "width": 2400,
        "height": 1600
      },
      "GPS": null
    },
    {
      "src": "/photos/kilimanjaro/kilimanjaro-35.jpg",
      "size": {
        "width": 2400,
        "height": 1600
      },
      "GPS": null
    },
    {
      "src": "/photos/kilimanjaro/kilimanjaro-36.jpg",
      "size": {
        "width": 2400,
        "height": 1600
      },
      "GPS": null
    },
    {
      "src": "/photos/kilimanjaro/kilimanjaro-37.jpg",
      "size": {
        "width": 2400,
        "height": 1600
      },
      "GPS": null
    },
    {
      "src": "/photos/kilimanjaro/kilimanjaro-38.jpg",
      "size": {
        "width": 2400,
        "height": 1600
      },
      "GPS": null
    },
    {
      "src": "/photos/kilimanjaro/kilimanjaro-39.jpg",
      "size": {
        "width": 2400,
        "height": 1600
      },
      "GPS": null
    },
    {
      "src": "/photos/kilimanjaro/kilimanjaro-40.jpg",
      "size": {
        "width": 2400,
        "height": 1600
      },
      "GPS": null
    }
  ],
  "malaysia": [
    {
      "src": "/photos/malaysia/malaisie-01.jpg",
      "size": {
        "width": 2400,
        "height": 1600
      },
      "GPS": null
    },
    {
      "src": "/photos/malaysia/malaisie-02.jpg",
      "size": {
        "width": 1067,
        "height": 1600
      },
      "GPS": null
    },
    {
      "src": "/photos/malaysia/malaisie-03.jpg",
      "size": {
        "width": 1067,
        "height": 1600
      },
      "GPS": null
    },
    {
      "src": "/photos/malaysia/malaisie-04.jpg",
      "size": {
        "width": 2400,
        "height": 1600
      },
      "GPS": null
    },
    {
      "src": "/photos/malaysia/malaisie-05.jpg",
      "size": {
        "width": 2400,
        "height": 1600
      },
      "GPS": null
    },
    {
      "src": "/photos/malaysia/malaisie-06.jpg",
      "size": {
        "width": 1067,
        "height": 1600
      },
      "GPS": null
    },
    {
      "src": "/photos/malaysia/malaisie-07.jpg",
      "size": {
        "width": 1067,
        "height": 1600
      },
      "GPS": null
    },
    {
      "src": "/photos/malaysia/malaisie-08.jpg",
      "size": {
        "width": 2400,
        "height": 1600
      },
      "GPS": null
    },
    {
      "src": "/photos/malaysia/malaisie-09.jpg",
      "size": {
        "width": 2400,
        "height": 1600
      },
      "GPS": null
    },
    {
      "src": "/photos/malaysia/malaisie-10.jpg",
      "size": {
        "width": 2400,
        "height": 1600
      },
      "GPS": null
    },
    {
      "src": "/photos/malaysia/malaisie-11.jpg",
      "size": {
        "width": 2400,
        "height": 1600
      },
      "GPS": null
    },
    {
      "src": "/photos/malaysia/malaisie-12.jpg",
      "size": {
        "width": 2400,
        "height": 1600
      },
      "GPS": null
    },
    {
      "src": "/photos/malaysia/malaisie-13.jpg",
      "size": {
        "width": 2400,
        "height": 1600
      },
      "GPS": null
    },
    {
      "src": "/photos/malaysia/malaisie-14.jpg",
      "size": {
        "width": 1067,
        "height": 1600
      },
      "GPS": null
    },
    {
      "src": "/photos/malaysia/malaisie-15.jpg",
      "size": {
        "width": 1067,
        "height": 1600
      },
      "GPS": null
    },
    {
      "src": "/photos/malaysia/malaisie-16.jpg",
      "size": {
        "width": 2400,
        "height": 1600
      },
      "GPS": null
    },
    {
      "src": "/photos/malaysia/malaisie-17.jpg",
      "size": {
        "width": 2400,
        "height": 1600
      },
      "GPS": null
    },
    {
      "src": "/photos/malaysia/malaisie-18.jpg",
      "size": {
        "width": 2400,
        "height": 1600
      },
      "GPS": null
    },
    {
      "src": "/photos/malaysia/malaisie-19.jpg",
      "size": {
        "width": 2400,
        "height": 1600
      },
      "GPS": null
    },
    {
      "src": "/photos/malaysia/malaisie-20.jpg",
      "size": {
        "width": 2400,
        "height": 1600
      },
      "GPS": null
    },
    {
      "src": "/photos/malaysia/malaisie-21.jpg",
      "size": {
        "width": 2400,
        "height": 1600
      },
      "GPS": null
    },
    {
      "src": "/photos/malaysia/malaisie-22.jpg",
      "size": {
        "width": 2400,
        "height": 1600
      },
      "GPS": null
    },
    {
      "src": "/photos/malaysia/malaisie-23.jpg",
      "size": {
        "width": 2400,
        "height": 1600
      },
      "GPS": null
    },
    {
      "src": "/photos/malaysia/malaisie-24.jpg",
      "size": {
        "width": 2400,
        "height": 1600
      },
      "GPS": null
    },
    {
      "src": "/photos/malaysia/malaisie-25.jpg",
      "size": {
        "width": 1067,
        "height": 1600
      },
      "GPS": null
    },
    {
      "src": "/photos/malaysia/malaisie-26.jpg",
      "size": {
        "width": 1067,
        "height": 1600
      },
      "GPS": null
    },
    {
      "src": "/photos/malaysia/malaisie-27.jpg",
      "size": {
        "width": 2400,
        "height": 1600
      },
      "GPS": null
    },
    {
      "src": "/photos/malaysia/malaisie-28.jpg",
      "size": {
        "width": 2400,
        "height": 1600
      },
      "GPS": null
    },
    {
      "src": "/photos/malaysia/malaisie-29.jpg",
      "size": {
        "width": 1068,
        "height": 1600
      },
      "GPS": null
    },
    {
      "src": "/photos/malaysia/malaisie-30.jpg",
      "size": {
        "width": 1067,
        "height": 1600
      },
      "GPS": null
    },
    {
      "src": "/photos/malaysia/malaisie-31.jpg",
      "size": {
        "width": 2400,
        "height": 1600
      },
      "GPS": null
    },
    {
      "src": "/photos/malaysia/malaisie-32.jpg",
      "size": {
        "width": 2400,
        "height": 1600
      },
      "GPS": null
    },
    {
      "src": "/photos/malaysia/malaisie-33.jpg",
      "size": {
        "width": 2400,
        "height": 1600
      },
      "GPS": null
    },
    {
      "src": "/photos/malaysia/malaisie-34.jpg",
      "size": {
        "width": 2400,
        "height": 1600
      },
      "GPS": null
    },
    {
      "src": "/photos/malaysia/malaisie-35.jpg",
      "size": {
        "width": 2400,
        "height": 1600
      },
      "GPS": null
    },
    {
      "src": "/photos/malaysia/malaisie-36.jpg",
      "size": {
        "width": 2400,
        "height": 1600
      },
      "GPS": null
    },
    {
      "src": "/photos/malaysia/malaisie-37.jpg",
      "size": {
        "width": 2400,
        "height": 1600
      },
      "GPS": null
    },
    {
      "src": "/photos/malaysia/malaisie-38.jpg",
      "size": {
        "width": 2400,
        "height": 1600
      },
      "GPS": null
    },
    {
      "src": "/photos/malaysia/malaisie-39.jpg",
      "size": {
        "width": 2400,
        "height": 1600
      },
      "GPS": null
    },
    {
      "src": "/photos/malaysia/malaisie-40.jpg",
      "size": {
        "width": 2400,
        "height": 1600
      },
      "GPS": null
    },
    {
      "src": "/photos/malaysia/malaisie-41.jpg",
      "size": {
        "width": 2400,
        "height": 1600
      },
      "GPS": null
    },
    {
      "src": "/photos/malaysia/malaisie-42.jpg",
      "size": {
        "width": 2400,
        "height": 1600
      },
      "GPS": null
    },
    {
      "src": "/photos/malaysia/malaisie-43.jpg",
      "size": {
        "width": 2400,
        "height": 1600
      },
      "GPS": null
    },
    {
      "src": "/photos/malaysia/malaisie-44.jpg",
      "size": {
        "width": 1067,
        "height": 1600
      },
      "GPS": null
    },
    {
      "src": "/photos/malaysia/malaisie-45.jpg",
      "size": {
        "width": 1067,
        "height": 1600
      },
      "GPS": null
    }
  ],
  "myanmar": [
    {
      "src": "/photos/myanmar/myanmar-01.jpg",
      "size": {
        "width": 2400,
        "height": 1600
      },
      "GPS": null
    },
    {
      "src": "/photos/myanmar/myanmar-02.jpg",
      "size": {
        "width": 1067,
        "height": 1600
      },
      "GPS": null
    },
    {
      "src": "/photos/myanmar/myanmar-03.jpg",
      "size": {
        "width": 1067,
        "height": 1600
      },
      "GPS": null
    },
    {
      "src": "/photos/myanmar/myanmar-04.jpg",
      "size": {
        "width": 2400,
        "height": 1600
      },
      "GPS": null
    },
    {
      "src": "/photos/myanmar/myanmar-05.jpg",
      "size": {
        "width": 1067,
        "height": 1600
      },
      "GPS": null
    },
    {
      "src": "/photos/myanmar/myanmar-06.jpg",
      "size": {
        "width": 1067,
        "height": 1600
      },
      "GPS": null
    },
    {
      "src": "/photos/myanmar/myanmar-07.jpg",
      "size": {
        "width": 2400,
        "height": 1600
      },
      "GPS": null
    },
    {
      "src": "/photos/myanmar/myanmar-08.jpg",
      "size": {
        "width": 1067,
        "height": 1600
      },
      "GPS": null
    },
    {
      "src": "/photos/myanmar/myanmar-09.jpg",
      "size": {
        "width": 1067,
        "height": 1600
      },
      "GPS": null
    },
    {
      "src": "/photos/myanmar/myanmar-10.jpg",
      "size": {
        "width": 2400,
        "height": 1600
      },
      "GPS": null
    },
    {
      "src": "/photos/myanmar/myanmar-11.jpg",
      "size": {
        "width": 2400,
        "height": 1600
      },
      "GPS": null
    },
    {
      "src": "/photos/myanmar/myanmar-12.jpg",
      "size": {
        "width": 2400,
        "height": 1600
      },
      "GPS": null
    },
    {
      "src": "/photos/myanmar/myanmar-13.jpg",
      "size": {
        "width": 2400,
        "height": 1600
      },
      "GPS": null
    },
    {
      "src": "/photos/myanmar/myanmar-14.jpg",
      "size": {
        "width": 2400,
        "height": 1600
      },
      "GPS": null
    },
    {
      "src": "/photos/myanmar/myanmar-15.jpg",
      "size": {
        "width": 2400,
        "height": 1600
      },
      "GPS": null
    },
    {
      "src": "/photos/myanmar/myanmar-16.jpg",
      "size": {
        "width": 1067,
        "height": 1600
      },
      "GPS": null
    },
    {
      "src": "/photos/myanmar/myanmar-17.jpg",
      "size": {
        "width": 1067,
        "height": 1600
      },
      "GPS": null
    },
    {
      "src": "/photos/myanmar/myanmar-18.jpg",
      "size": {
        "width": 2400,
        "height": 1600
      },
      "GPS": null
    },
    {
      "src": "/photos/myanmar/myanmar-19.jpg",
      "size": {
        "width": 1066,
        "height": 1600
      },
      "GPS": null
    },
    {
      "src": "/photos/myanmar/myanmar-20.jpg",
      "size": {
        "width": 1067,
        "height": 1600
      },
      "GPS": null
    },
    {
      "src": "/photos/myanmar/myanmar-21.jpg",
      "size": {
        "width": 2400,
        "height": 1600
      },
      "GPS": null
    },
    {
      "src": "/photos/myanmar/myanmar-22.jpg",
      "size": {
        "width": 1067,
        "height": 1600
      },
      "GPS": null
    },
    {
      "src": "/photos/myanmar/myanmar-23.jpg",
      "size": {
        "width": 1067,
        "height": 1600
      },
      "GPS": null
    },
    {
      "src": "/photos/myanmar/myanmar-24.jpg",
      "size": {
        "width": 2400,
        "height": 1600
      },
      "GPS": null
    },
    {
      "src": "/photos/myanmar/myanmar-25.jpg",
      "size": {
        "width": 1067,
        "height": 1600
      },
      "GPS": null
    },
    {
      "src": "/photos/myanmar/myanmar-26.jpg",
      "size": {
        "width": 1067,
        "height": 1600
      },
      "GPS": null
    },
    {
      "src": "/photos/myanmar/myanmar-27.jpg",
      "size": {
        "width": 2400,
        "height": 1600
      },
      "GPS": null
    },
    {
      "src": "/photos/myanmar/myanmar-28.jpg",
      "size": {
        "width": 2400,
        "height": 1600
      },
      "GPS": null
    },
    {
      "src": "/photos/myanmar/myanmar-29.jpg",
      "size": {
        "width": 2400,
        "height": 1600
      },
      "GPS": null
    },
    {
      "src": "/photos/myanmar/myanmar-30.jpg",
      "size": {
        "width": 2400,
        "height": 1600
      },
      "GPS": null
    },
    {
      "src": "/photos/myanmar/myanmar-31.jpg",
      "size": {
        "width": 2400,
        "height": 1600
      },
      "GPS": null
    },
    {
      "src": "/photos/myanmar/myanmar-32.jpg",
      "size": {
        "width": 2400,
        "height": 1600
      },
      "GPS": null
    },
    {
      "src": "/photos/myanmar/myanmar-33.jpg",
      "size": {
        "width": 2400,
        "height": 1600
      },
      "GPS": null
    },
    {
      "src": "/photos/myanmar/myanmar-34.jpg",
      "size": {
        "width": 2400,
        "height": 1600
      },
      "GPS": null
    },
    {
      "src": "/photos/myanmar/myanmar-35.jpg",
      "size": {
        "width": 1067,
        "height": 1600
      },
      "GPS": null
    },
    {
      "src": "/photos/myanmar/myanmar-36.jpg",
      "size": {
        "width": 1067,
        "height": 1600
      },
      "GPS": null
    },
    {
      "src": "/photos/myanmar/myanmar-37.jpg",
      "size": {
        "width": 2400,
        "height": 1600
      },
      "GPS": null
    },
    {
      "src": "/photos/myanmar/myanmar-38.jpg",
      "size": {
        "width": 2400,
        "height": 1600
      },
      "GPS": null
    },
    {
      "src": "/photos/myanmar/myanmar-39.jpg",
      "size": {
        "width": 2400,
        "height": 1600
      },
      "GPS": null
    },
    {
      "src": "/photos/myanmar/myanmar-40.jpg",
      "size": {
        "width": 2400,
        "height": 1600
      },
      "GPS": null
    },
    {
      "src": "/photos/myanmar/myanmar-41.jpg",
      "size": {
        "width": 2400,
        "height": 1600
      },
      "GPS": null
    },
    {
      "src": "/photos/myanmar/myanmar-42.jpg",
      "size": {
        "width": 1067,
        "height": 1600
      },
      "GPS": null
    },
    {
      "src": "/photos/myanmar/myanmar-43.jpg",
      "size": {
        "width": 1067,
        "height": 1600
      },
      "GPS": null
    },
    {
      "src": "/photos/myanmar/myanmar-44.jpg",
      "size": {
        "width": 2400,
        "height": 1600
      },
      "GPS": null
    },
    {
      "src": "/photos/myanmar/myanmar-45.jpg",
      "size": {
        "width": 2400,
        "height": 1600
      },
      "GPS": null
    },
    {
      "src": "/photos/myanmar/myanmar-46.jpg",
      "size": {
        "width": 1067,
        "height": 1600
      },
      "GPS": null
    },
    {
      "src": "/photos/myanmar/myanmar-47.jpg",
      "size": {
        "width": 1067,
        "height": 1600
      },
      "GPS": null
    },
    {
      "src": "/photos/myanmar/myanmar-48.jpg",
      "size": {
        "width": 2400,
        "height": 1600
      },
      "GPS": null
    },
    {
      "src": "/photos/myanmar/myanmar-49.jpg",
      "size": {
        "width": 2400,
        "height": 1600
      },
      "GPS": null
    },
    {
      "src": "/photos/myanmar/myanmar-50.jpg",
      "size": {
        "width": 1067,
        "height": 1600
      },
      "GPS": null
    },
    {
      "src": "/photos/myanmar/myanmar-51.jpg",
      "size": {
        "width": 1067,
        "height": 1600
      },
      "GPS": null
    },
    {
      "src": "/photos/myanmar/myanmar-52.jpg",
      "size": {
        "width": 2400,
        "height": 1600
      },
      "GPS": null
    },
    {
      "src": "/photos/myanmar/myanmar-53.jpg",
      "size": {
        "width": 2400,
        "height": 1600
      },
      "GPS": null
    },
    {
      "src": "/photos/myanmar/myanmar-54.jpg",
      "size": {
        "width": 2400,
        "height": 1600
      },
      "GPS": null
    },
    {
      "src": "/photos/myanmar/myanmar-55.jpg",
      "size": {
        "width": 1067,
        "height": 1600
      },
      "GPS": null
    },
    {
      "src": "/photos/myanmar/myanmar-56.jpg",
      "size": {
        "width": 1067,
        "height": 1600
      },
      "GPS": null
    },
    {
      "src": "/photos/myanmar/myanmar-57.jpg",
      "size": {
        "width": 2400,
        "height": 1600
      },
      "GPS": null
    }
  ],
  "nepal": [
    {
      "src": "/photos/nepal/nepal-01.jpg",
      "size": {
        "width": 1067,
        "height": 1600
      },
      "GPS": null
    },
    {
      "src": "/photos/nepal/nepal-02.jpg",
      "size": {
        "width": 1067,
        "height": 1600
      },
      "GPS": null
    },
    {
      "src": "/photos/nepal/nepal-03.jpg",
      "size": {
        "width": 2400,
        "height": 1600
      },
      "GPS": null
    },
    {
      "src": "/photos/nepal/nepal-04.jpg",
      "size": {
        "width": 1067,
        "height": 1600
      },
      "GPS": null
    },
    {
      "src": "/photos/nepal/nepal-05.jpg",
      "size": {
        "width": 1067,
        "height": 1600
      },
      "GPS": null
    },
    {
      "src": "/photos/nepal/nepal-06.jpg",
      "size": {
        "width": 2400,
        "height": 1600
      },
      "GPS": {
        "lat": 27.721327764269574,
        "lng": 85.3618983671171
      }
    },
    {
      "src": "/photos/nepal/nepal-07.jpg",
      "size": {
        "width": 1067,
        "height": 1600
      },
      "GPS": null
    },
    {
      "src": "/photos/nepal/nepal-08.jpg",
      "size": {
        "width": 1067,
        "height": 1600
      },
      "GPS": null
    },
    {
      "src": "/photos/nepal/nepal-09.jpg",
      "size": {
        "width": 2400,
        "height": 1600
      },
      "GPS": null
    },
    {
      "src": "/photos/nepal/nepal-10.jpg",
      "size": {
        "width": 2400,
        "height": 1600
      },
      "GPS": {
        "lat": 27.673830065803376,
        "lng": 85.43116877414823
      }
    },
    {
      "src": "/photos/nepal/nepal-11.jpg",
      "size": {
        "width": 2400,
        "height": 1600
      },
      "GPS": null
    },
    {
      "src": "/photos/nepal/nepal-12.jpg",
      "size": {
        "width": 1067,
        "height": 1600
      },
      "GPS": null
    },
    {
      "src": "/photos/nepal/nepal-13.jpg",
      "size": {
        "width": 1067,
        "height": 1600
      },
      "GPS": null
    },
    {
      "src": "/photos/nepal/nepal-14.jpg",
      "size": {
        "width": 2400,
        "height": 1600
      },
      "GPS": null
    },
    {
      "src": "/photos/nepal/nepal-15.jpg",
      "size": {
        "width": 2400,
        "height": 1600
      },
      "GPS": {
        "lat": 27.718189450643642,
        "lng": 85.51875616944037
      }
    },
    {
      "src": "/photos/nepal/nepal-16.jpg",
      "size": {
        "width": 2400,
        "height": 1600
      },
      "GPS": null
    },
    {
      "src": "/photos/nepal/nepal-17.jpg",
      "size": {
        "width": 1067,
        "height": 1600
      },
      "GPS": null
    },
    {
      "src": "/photos/nepal/nepal-18.jpg",
      "size": {
        "width": 1067,
        "height": 1600
      },
      "GPS": null
    }
  ],
  "thailand": [
    {
      "src": "/photos/thailand/thailand-01.jpg",
      "size": {
        "width": 2400,
        "height": 1600
      },
      "GPS": null
    },
    {
      "src": "/photos/thailand/thailand-02.jpg",
      "size": {
        "width": 1067,
        "height": 1600
      },
      "GPS": null
    },
    {
      "src": "/photos/thailand/thailand-03.jpg",
      "size": {
        "width": 1067,
        "height": 1600
      },
      "GPS": null
    },
    {
      "src": "/photos/thailand/thailand-04.jpg",
      "size": {
        "width": 2400,
        "height": 1600
      },
      "GPS": null
    },
    {
      "src": "/photos/thailand/thailand-05.jpg",
      "size": {
        "width": 2400,
        "height": 1600
      },
      "GPS": {
        "lat": 13.817697569974056,
        "lng": 100.55835664028145
      }
    },
    {
      "src": "/photos/thailand/thailand-06.jpg",
      "size": {
        "width": 2400,
        "height": 1600
      },
      "GPS": null
    },
    {
      "src": "/photos/thailand/thailand-07.jpg",
      "size": {
        "width": 1067,
        "height": 1600
      },
      "GPS": null
    },
    {
      "src": "/photos/thailand/thailand-08.jpg",
      "size": {
        "width": 1067,
        "height": 1600
      },
      "GPS": null
    },
    {
      "src": "/photos/thailand/thailand-09.jpg",
      "size": {
        "width": 2400,
        "height": 1600
      },
      "GPS": null
    },
    {
      "src": "/photos/thailand/thailand-10.jpg",
      "size": {
        "width": 2400,
        "height": 1600
      },
      "GPS": null
    },
    {
      "src": "/photos/thailand/thailand-11.jpg",
      "size": {
        "width": 2400,
        "height": 1600
      },
      "GPS": null
    },
    {
      "src": "/photos/thailand/thailand-12.jpg",
      "size": {
        "width": 1067,
        "height": 1600
      },
      "GPS": null
    },
    {
      "src": "/photos/thailand/thailand-13.jpg",
      "size": {
        "width": 1067,
        "height": 1600
      },
      "GPS": {
        "lat": 11.678812289993735,
        "lng": 102.54961144898157
      }
    },
    {
      "src": "/photos/thailand/thailand-14.jpg",
      "size": {
        "width": 2400,
        "height": 1600
      },
      "GPS": null
    },
    {
      "src": "/photos/thailand/thailand-15.jpg",
      "size": {
        "width": 1067,
        "height": 1600
      },
      "GPS": null
    },
    {
      "src": "/photos/thailand/thailand-16.jpg",
      "size": {
        "width": 1067,
        "height": 1600
      },
      "GPS": null
    },
    {
      "src": "/photos/thailand/thailand-17.jpg",
      "size": {
        "width": 2400,
        "height": 1600
      },
      "GPS": null
    }
  ]
}